{
  "type": "tconstruct:swappable_modifier",
  "allow_crystal": false,
  "conditions": [
    {
      "type": "forge:not",
      "value": {
        "type": "forge:tag_empty",
        "tag": "forge:ingots/bronze"
      }
    }
  ],
  "inputs": [
    {
      "tag": "forge:ingots/bronze"
    },
    {
      "tag": "forge:ingots/bronze"
    },
    {
      "tag": "forge:ingots/bronze"
    }
  ],
  "result": {
    "name": "tconstruct:embellishment",
    "value": "tconstruct:bronze"
  },
  "tools": {
    "tag": "tconstruct:modifiable/embellishment/metal"
  }
}