{
  "type": "forge:conditional",
  "recipes": [
    {
      "conditions": [
        {
          "pulseid": "tinker_gadgets",
          "type": "tconstruct:pulse_loaded"
        }
      ],
      "recipe": {
        "type": "minecraft:crafting_shaped",
        "group": "tconstruct:slime_boots",
        "pattern": [
          "X X",
          "# #"
        ],
        "key": {
          "#": {
            "item": "tconstruct:congealed_magma_slime"
          },
          "X": {
            "tag": "forge:slimeball/magma"
          }
        },
        "result": {
          "item": "tconstruct:slime_boots_magma"
        }
      }
    }
  ]
}