{
    "conditions": [
        {
            "type": "tconstruct:is_pulse_loaded",
            "pulse_name": "TinkerGadgets"
        }
    ],
    "type": "forge:ore_shaped",
    "pattern": [
        "AAA",
        "ABA",
        "AAA"
    ],
    "key": {
        "A": {
            "item": "minecraft:snowball"
        },
        "B": {
            "type": "forge:ore_dict",
            "ore": "dustGlowstone"
        }
    },
    "result": {
        "item": "tconstruct:throwball",
        "count": 8,
        "data": 0
    }
}