{
  "modifier_id": "tconstruct:looting",
  "text": [
    {
      "text": "Увеличивает частоту выпавших предметов из монстров, убитые пустой рукой. Везение требует другой уровень для каждого уровня, наложенный по порядку."
    },
    {
      "text": "Инструменты могут получить либо везение либо добычу, исходя от того, сможет ли он ломать блоки.",
      "paragraph": true
    }
  ],
  "more_text_space": true,
  "effects": [
    "Не более 3 уровней.",
    "Первый уровень требует 1 слот умения.",
    "Второй и третий уровень безслотовый."
  ]
}