{
  "modifier_id": "tconstruct:looting",
  "text": [
    {
      "text": "Увеличивает количество выпадающих предметов с монстров, убитых пустой рукой. Обратите внимание, что в отличие от других модификаторов, которые имеют несколько рецептов, удача имеет отдельный рецепт для каждого уровня, и рецепты должны применяться по порядку."
    }
  ],
  "more_text_space": true,
  "effects": [
    "Максимум 3 уровня",
    "Требуется 1 слот для улучшения за уровень",
    "Требуется модификатор Безоружная Атака"
  ]
}
