{
  "stats": {
    "tconstruct:extra": {},
    "tconstruct:grip": {
      "accuracy": -0.2,
      "durability": 1.4,
      "meleeAttack": 1.0
    },
    "tconstruct:handle": {
      "attackDamage": 0.85,
      "attackSpeed": 1.0,
      "durability": 1.3,
      "miningSpeed": 0.85
    },
    "tconstruct:head": {
      "attack": 1.0,
      "durability": 375,
      "harvestTier": "minecraft:iron",
      "miningSpeed": 4.0
    },
    "tconstruct:limb": {
      "accuracy": 0.1,
      "drawSpeed": 0.0,
      "durability": 375,
      "velocity": -0.05
    }
  }
}