{
  "parent": "minecraft:recipes/root",
  "rewards": {
    "recipes": [
      "tconstruct:world/wood/bloodshroom/stripped_log_to_wood"
    ]
  },
  "criteria": {
    "has_log": {
      "trigger": "minecraft:inventory_changed",
      "conditions": {
        "items": [
          {
            "item": "tconstruct:stripped_bloodshroom_log"
          }
        ]
      }
    },
    "has_the_recipe": {
      "trigger": "minecraft:recipe_unlocked",
      "conditions": {
        "recipe": "tconstruct:world/wood/bloodshroom/stripped_log_to_wood"
      }
    }
  },
  "requirements": [
    [
      "has_log",
      "has_the_recipe"
    ]
  ]
}