<?xml version="1.0"?>
<!DOCTYPE properties SYSTEM "http://java.sun.com/dtd/properties.dtd">
<properties version = "1.0">
  <entry key="itemGroup.TConstructTools">TConstruct Tools</entry>
  <entry key="itemGroup.TConstructMaterials">TConstruct Materials</entry>
  <entry key="itemGroup.TConstructBlocks">TConstruct Blocks</entry>
  
  <entry key="crafters.ToolStation">Tool Station</entry>
  <entry key="crafters.ToolForge">Tool Forge</entry>
  <entry key="crafters.PartBuilder">Part Builder</entry>
  <entry key="crafters.PatternShaper">Stencil Table</entry>
  <entry key="inventory.PatternChest">Pattern Chest</entry>
  <entry key="crafters.Smeltery">Smeltery</entry>
  <entry key="crafters.Frypan">Frying Pan</entry>
  <entry key="inventory.knapsack">Knapsack</entry>
  
  <entry key="ToolStation.Crafter.name">Tool Station</entry>
  <entry key="ToolStation.Parts.name">Part Builder</entry>
  <entry key="ToolStation.PatternChest.name">Pattern Chest</entry>
  <entry key="ToolStation.PatternShaper.name">Stencil Table</entry>
  <entry key="ToolStation.CastingTable.name">Casting Table</entry>
  
  <entry key="tile.ToolForge.name">Tool Forge</entry>
  <entry key="tile.Armor.DryingRack.name">Drying Rack</entry>
  <entry key="CraftedSoil.Slime.name">Slimy Mud</entry>
  <entry key="CraftedSoil.Grout.name">Grout</entry>
  <entry key="CraftedSoil.BlueSlime.name">Slimy Mud</entry>
  <entry key="CraftedSoil.GraveyardSoil.name">Graveyard Soil</entry>
  <entry key="CraftedSoil.ConsecratedSoil.name">Consecrated Soil</entry>
  
  <entry key="MetalOre.NetherSlag.name">Netherack Slag</entry>
  <entry key="MetalOre.Cobalt.name">Cobalt Ore</entry>
  <entry key="MetalOre.Ardite.name">Ardite Ore</entry>
  <entry key="MetalOre.Copper.name">Copper Ore</entry>
  <entry key="MetalOre.Tin.name">Tin Ore</entry>
  <entry key="MetalOre.Aluminum.name">Aluminum Ore</entry>
  <entry key="MetalOre.Slag.name">Stone Slag</entry>
  
  <entry key="block.oreberry.iron.name">Iron Oreberry Bush</entry>
  <entry key="block.oreberry.gold.name">Gold Oreberry Bush</entry>
  <entry key="block.oreberry.copper.name">Copper Oreberry Bush</entry>
  <entry key="block.oreberry.tin.name">Tin Oreberry Bush</entry>
  <entry key="block.oreberry.aluminum.name">Aluminum Oreberry Bush</entry>
  <entry key="block.oreberry.essence.name">Essence Oreberry Bush</entry>
  
  <entry key="block.ore.gravel.iron.name">Iron Gravel Ore</entry>
  <entry key="block.ore.gravel.gold.name">Gold Gravel Ore</entry>
  <entry key="block.ore.gravel.copper.name">Copper Gravel Ore</entry>
  <entry key="block.ore.gravel.tin.name">Tin Gravel Ore</entry>
  <entry key="block.ore.gravel.aluminum.name">Aluminum Gravel Ore</entry>
  <entry key="block.ore.gravel.cobalt.name">Cobalt Gravel Ore</entry>
    
  <entry key="block.brownstone.rough.name">Rough Brownstone</entry>
  <entry key="block.brownstone.rough.road.name">Brownstone Road</entry>
  <entry key="block.brownstone.smooth.name">Brownstone</entry>
  <entry key="block.brownstone.smooth.brick.name">Brownstone Brick</entry>
  <entry key="block.brownstone.smooth.road.name">Brownstone Road</entry>
  <entry key="block.brownstone.smooth.fancy.name">Fancy Brownstone</entry>
  <entry key="block.brownstone.smooth.chiseled.name">Chiseled Brownstone</entry>
  
  <entry key="block.brownstone.rough.slab.name">Rough Brownstone Slab</entry>
  <entry key="block.brownstone.rough.road.slab.name">Brownstone Road Slab</entry>
  <entry key="block.brownstone.smooth.slab.name">Brownstone Slab</entry>
  <entry key="block.brownstone.smooth.brick.slab.name">Brownstone Brick Slab</entry>
  <entry key="block.brownstone.smooth.road.slab.name">Brownstone Road Slab</entry>
  <entry key="block.brownstone.smooth.fancy.slab.name">Fancy Brownstone Slab</entry>
  <entry key="block.brownstone.smooth.chiseled.slab.name">Chiseled Brownstone Slab</entry>
  
  <entry key="block.brick.obsidian.name">Obsidian Brick</entry>
  <entry key="block.brick.sandstone.name">Sandstone Brick</entry>
  <entry key="block.brick.netherrack.name">Netherrack Brick</entry>
  <entry key="block.brick.iron.name">Iron Brick</entry>
  <entry key="block.brick.gold.name">Gold Brick</entry>
  <entry key="block.brick.diamond.name">Diamond Brick</entry>
  <entry key="block.brick.lapis.name">Lapis Brick</entry>
  <entry key="block.brick.stone.refined.name">Polished Stone Brick</entry>
  <entry key="block.brick.redstone.name">Redstone Brick</entry>
  <entry key="block.brick.bone.name">Bone Brick</entry>
  <entry key="block.brick.slime.name">Slime Brick</entry>
  <entry key="block.brick.blueslime.name">Slime Brick</entry>
  <entry key="block.brick.endstone.name">Endstone Brick</entry>
  <entry key="block.brick.obsidian.ingot.name">Obsidian Brick</entry>
  
  <entry key="block.fancybrick.obsidian.name">Fancy Obsidian Brick</entry>
  <entry key="block.fancybrick.sandstone.name">Fancy Sandstone Brick</entry>
  <entry key="block.fancybrick.netherrack.name">Fancy Netherrack Brick</entry>
  <entry key="block.fancybrick.iron.name">Fancy Iron Brick</entry>
  <entry key="block.fancybrick.gold.name">Fancy Gold Brick</entry>
  <entry key="block.fancybrick.diamond.name">Fancy Diamond Brick</entry>
  <entry key="block.fancybrick.lapis.name">Fancy Lapis Brick</entry>
  <entry key="block.fancybrick.stone.refined.name">Fancy Polished Stone Brick</entry>
  <entry key="block.fancybrick.redstone.name">Fancy Redstone Brick</entry>
  <entry key="block.fancybrick.bone.name">Fancy Bone Brick</entry>
  <entry key="block.fancybrick.slime.name">Fancy Slime Brick</entry>
  <entry key="block.fancybrick.blueslime.name">Fancy Slime Brick</entry>
  <entry key="block.fancybrick.endstone.name">Fancy Endstone Brick</entry>
  <entry key="block.fancybrick.obsidian.ingot.name">Fancy Obsidian Brick</entry>
  <entry key="block.fancybrick.stone.road.name">Stone Road</entry>
  <entry key="block.fancybrick.stone.name">Fancy Stone Brick</entry>
  
  <entry key="item.oreberry.iron.name">Iron Oreberry</entry>
  <entry key="item.oreberry.gold.name">Gold Oreberry</entry>
  <entry key="item.oreberry.copper.name">Copper Oreberry</entry>
  <entry key="item.oreberry.tin.name">Tin Oreberry</entry>
  <entry key="item.oreberry.aluminum.name">Aluminum Oreberry</entry>
  <entry key="item.oreberry.essence.name">Concentrated Essence Berry</entry>
  
  <entry key="item.goldenhead.name">Golden Head</entry>
  <entry key="item.tconstruct.titleicon.name">Spawn </entry>
  
  <entry key="item.tconstruct.Materials.PaperStack.name">Paper Stack</entry>
  <entry key="item.tconstruct.Materials.SlimeCrystal.name">Slime Crystal</entry>
  <entry key="item.tconstruct.Materials.SearedBrick.name">Seared Brick</entry>
  <entry key="item.tconstruct.Materials.CobaltIngot.name">Cobalt Ingot</entry>
  <entry key="item.tconstruct.Materials.ArditeIngot.name">Ardite Ingot</entry>
  <entry key="item.tconstruct.Materials.ManyullynIngot.name">Manyullyn Ingot</entry>
  <entry key="item.tconstruct.Materials.Mossball.name">Ball of Moss</entry>
  <entry key="item.tconstruct.Materials.LavaCrystal.name">Lava Crystal</entry>
  <entry key="item.tconstruct.Materials.NecroticBone.name">Necrotic Bone</entry>
  <entry key="item.tconstruct.Materials.CopperIngot.name">Copper Ingot</entry>
  <entry key="item.tconstruct.Materials.TinIngot.name">Tin Ingot</entry>
  <entry key="item.tconstruct.Materials.AluminumIngot.name">Aluminum Ingot</entry>
  <entry key="item.tconstruct.Materials.RawAluminum.name">Raw Aluminum</entry>
  <entry key="item.tconstruct.Materials.BronzeIngot.name">Bronze Ingot</entry>
  <entry key="item.tconstruct.Materials.AluBrassIngot.name">Aluminum Brass Ingot</entry>
  <entry key="item.tconstruct.Materials.AlumiteIngot.name">Alumite Ingot</entry>
  <entry key="item.tconstruct.Materials.SteelIngot.name">Steel Ingot</entry>
  <entry key="item.tconstruct.Materials.BlueSlimeCrystal.name">Slime Crystal</entry>
  <entry key="item.tconstruct.Materials.ObsidianIngot.name">Obsidian Ingot</entry>
  <entry key="item.tconstruct.Materials.IronNugget.name">Iron Nugget</entry>
  <entry key="item.tconstruct.Materials.CopperNugget.name">Copper Nugget</entry>
  <entry key="item.tconstruct.Materials.TinNugget.name">Tin Nugget</entry>
  <entry key="item.tconstruct.Materials.AluminumNugget.name">Aluminum Nugget</entry>
  <entry key="item.tconstruct.Materials.EssenceCrystal.name">Essence Crystal</entry>
  <entry key="item.tconstruct.Materials.AluBrassNugget.name">Aluminum Brass Nugget</entry>
  <entry key="item.tconstruct.Materials.SilkyCloth.name">Silky Cloth</entry>
  <entry key="item.tconstruct.Materials.SilkyJewel.name">Silky Jewel</entry>
  
  <entry key="Smeltery.Controller.name">Smeltery Controller</entry>
  <entry key="Smeltery.Drain.name">Smeltery Drain</entry>
  <entry key="Smeltery.Brick.name">Seared Bricks</entry>
  <entry key="Smeltery.Stone.name">Seared Stone</entry>
  <entry key="Smeltery.Cobblestone.name">Seared Cobblestone</entry>
  <entry key="Smeltery.Paver.name">Seared Paver</entry>
  <entry key="Smeltery.Brick.Cracked.name">Cracked Seared Bricks</entry>
  <entry key="Smeltery.Road.name">Seared Road</entry>
  <entry key="Smeltery.Brick.Fancy.name">Fancy Seared Bricks</entry>
  <entry key="Smeltery.Brick.Square.name">Chiseled Seared Bricks</entry>
  <entry key="Smeltery.Brick.Creeper.name">Chiseled Seared Bricks</entry>
  
  <entry key="LavaTank.Tank.name">Seared Tank</entry>
  <entry key="LavaTank.Gague.name">Seared Glass</entry>
  <entry key="LavaTank.Window.name">Seared Window</entry>
  
  <entry key="block.drawbridge.name">Drawbridge</entry>
  <entry key="block.firestarter.name">Igniter</entry>
  <entry key="tile.landmine.name">Landmine</entry>
  
  <entry key="StorageMetals.Cobalt.name">Block of Cobalt</entry>
  <entry key="StorageMetals.Ardite.name">Block of Ardite</entry>
  <entry key="StorageMetals.Manyullyn.name">Block of Manyullyn</entry>
  <entry key="StorageMetals.Copper.name">Block of Copper</entry>
  <entry key="StorageMetals.Bronze.name">Block of Bronze</entry>
  <entry key="StorageMetals.Tin.name">Block of Tin</entry>
  <entry key="StorageMetals.Aluminum.name">Block of Aluminum</entry>
  <entry key="StorageMetals.AlBrass.name">Block of Aluminum Brass</entry>
  <entry key="StorageMetals.Alumite.name">Block of Alumite</entry>
  <entry key="StorageMetals.Steel.name">Block of Steel</entry>
  
  <entry key="tile.decoration.stonetorch.name">Torch</entry>
  
  <entry key="block.glass.pure.name">Clear Glass</entry>
  <entry key="block.glass.soul.name">Soul Glass</entry>
  <entry key="block.glass.soul.pure.name">Clear Soul Glass</entry>
  
  <entry key="block.glass.pure.pane.name">Clear Pane</entry>
  <entry key="block.glass.soul.pane.name">Soul Pane</entry>
  <entry key="block.glass.soul.pane.pure.name">Clear Soul Pane</entry>
  
  <entry key="block.stainedglass.white.name">White Stained Glass</entry>
  <entry key="block.stainedglass.orange.name">Orange Stained Glass</entry>
  <entry key="block.stainedglass.magenta.name">Magenta Stained Glass</entry>
  <entry key="block.stainedglass.lightblue.name">Light Blue Stained Glass</entry>
  <entry key="block.stainedglass.yellow.name">Yellow Stained Glass</entry>
  <entry key="block.stainedglass.lime.name">Lime Stained Glass</entry>
  <entry key="block.stainedglass.pink.name">Pink Stained Glass</entry>
  <entry key="block.stainedglass.gray.name">Gray Stained Glass</entry>
  <entry key="block.stainedglass.lightgray.name">Light Gray Stained Glass</entry>
  <entry key="block.stainedglass.cyan.name">Cyan Stained Glass</entry>
  <entry key="block.stainedglass.purple.name">Purple Stained Glass</entry>
  <entry key="block.stainedglass.blue.name">Blue Stained Glass</entry>
  <entry key="block.stainedglass.brown.name">Brown Stained Glass</entry>
  <entry key="block.stainedglass.green.name">Green Stained Glass</entry>
  <entry key="block.stainedglass.red.name">Red Stained Glass</entry>
  <entry key="block.stainedglass.black.name">Black Stained Glass</entry>
  
  <entry key="block.stainedglass.white.pane.name">White Stained Pane</entry>
  <entry key="block.stainedglass.orange.pane.name">Orange Stained Pane</entry>
  <entry key="block.stainedglass.magenta.pane.name">Magenta Stained Pane</entry>
  <entry key="block.stainedglass.lightblue.pane.name">Light Blue Stained Pane</entry>
  <entry key="block.stainedglass.yellow.pane.name">Yellow Stained Pane</entry>
  <entry key="block.stainedglass.lime.pane.name">Lime Stained Pane</entry>
  <entry key="block.stainedglass.pink.pane.name">Pink Stained Pane</entry>
  <entry key="block.stainedglass.gray.pane.name">Gray Stained Pane</entry>
  <entry key="block.stainedglass.lightgray.pane.name">Light Gray Stained Pane</entry>
  <entry key="block.stainedglass.cyan.pane.name">Cyan Stained Pane</entry>
  <entry key="block.stainedglass.purple.pane.name">Purple Stained Pane</entry>
  <entry key="block.stainedglass.blue.pane.name">Blue Stained Pane</entry>
  <entry key="block.stainedglass.brown.pane.name">Brown Stained Pane</entry>
  <entry key="block.stainedglass.green.pane.name">Green Stained Pane</entry>
  <entry key="block.stainedglass.red.pane.name">Red Stained Pane</entry>
  <entry key="block.stainedglass.black.pane.name">Black Stained Pane</entry>
  
  <entry key="block.searedstone.slab.brick.name">Seared Brick Slab</entry>
  <entry key="block.searedstone.slab.stone.name">Seared Stone Slab</entry>
  <entry key="block.searedstone.slab.cobble.name">Seared Cobblestone Slab</entry>
  <entry key="block.searedstone.slab.paver.name">Seared Paver Slab</entry>
  <entry key="block.searedstone.slab.road.name">Seared Road Slab</entry>
  <entry key="block.searedstone.slab.fancy.name">Fancy Seared Slab</entry>
  <entry key="block.searedstone.slab.square.name">Chiseled Seared Slab</entry>
  <entry key="block.searedstone.slab.creeper.name">Chiseled Seared Slab</entry>
  
  <entry key="block.soil.slab.dirt.name">Dirt Slab</entry>
  <entry key="block.soil.slab.mycelium.name">Full Mycelium Slab</entry>
  <entry key="block.soil.slab.slime.name">Slimy Mud Slab</entry>
  <entry key="block.soil.slab.grout.name">Grout Slab</entry>
  <entry key="block.soil.slab.blueslime.name">Slimy Mud Slab</entry>
  <entry key="block.soil.slab.graveyardsoil.name">Graveyard Soil Slab</entry>
  <entry key="block.soil.slab.consecratedsoil.name">Consecrated Soil Slab</entry>
  
  <entry key="item.tconstruct.storage.knapsack.name">Knapsack</entry>  
  <entry key="item.tconstruct.blankpattern.pattern.name">Blank Pattern</entry>
  <entry key="item.tconstruct.blankpattern.cast.name">Blank Cast</entry>
  
  <entry key="item.tconstruct.Bowstring.string.name">Bowstring</entry>
  <entry key="item.tconstruct.Bowstring.enchantedfabric.name">Enchanted Bowstring</entry>
  <entry key="item.tconstruct.Fletching.feather.name">Feather Fletching</entry>
  <entry key="item.tconstruct.Fletching.leaf.name">Leaf Fletching</entry>
  <entry key="item.tconstruct.Fletching.slime.name">Slime Fletching</entry>
  <entry key="item.tconstruct.Fletching.blueslime.name">Slime Fletching</entry>
  
  <entry key="item.tconstruct.manual.beginner.name">Materials and You</entry>
  <entry key="item.tconstruct.manual.toolstation.name">Materials and You</entry>
  <entry key="item.tconstruct.manual.smeltery.name">Mighty Smelting</entry>
  
  <entry key="item.tconstruct.bucket.Iron.name">Molten Iron Bucket</entry>
  <entry key="item.tconstruct.bucket.Gold.name">Molten Gold Bucket</entry>
  <entry key="item.tconstruct.bucket.Copper.name">Molten Copper Bucket</entry>
  <entry key="item.tconstruct.bucket.Tin.name">Molten Tin Bucket</entry>
  <entry key="item.tconstruct.bucket.Aluminum.name">Molten Aluminum Bucket</entry>
  <entry key="item.tconstruct.bucket.Cobalt.name">Molten Cobalt Bucket</entry>
  <entry key="item.tconstruct.bucket.Ardite.name">Molten Ardite Bucket</entry>
  <entry key="item.tconstruct.bucket.Bronze.name">Molten Bronze Bucket</entry>
  <entry key="item.tconstruct.bucket.AluBrass.name">Molten Aluminum Brass Bucket</entry>
  <entry key="item.tconstruct.bucket.Manyullyn.name">Molten Manyullyn Bucket</entry>
  <entry key="item.tconstruct.bucket.Alumite.name">Molten Alumite Bucket</entry>
  <entry key="item.tconstruct.bucket.Obsidian.name">Molten Obsidian Bucket</entry>
  <entry key="item.tconstruct.bucket.Steel.name">Molten Steel Bucket</entry>
  <entry key="item.tconstruct.bucket.Glass.name">Molten Glass Bucket</entry>
  <entry key="item.tconstruct.bucket.Stone.name">Seared Stone Bucket</entry>
  <entry key="item.tconstruct.bucket.Villager.name">Liquified Emerald Bucket</entry>
  <entry key="item.tconstruct.bucket.Cow.name">Bucket o' Blood</entry>
  
  <entry key="item.tconstruct.bowstring.string.name">Bowstring</entry>
  <entry key="item.tconstruct.bowstring.enchantedfabriI donc.name">Enchanted Bowstring</entry>
  
  <entry key="LiquidMetal.Iron.name">Molten Iron</entry>
  <entry key="LiquidMetal.Gold.name">Molten Gold</entry>
  <entry key="LiquidMetal.Copper.name">Molten Copper</entry>
  <entry key="LiquidMetal.Tin.name">Liquid Tin</entry>
  <entry key="LiquidMetal.Aluminum.name">Molten Aluminum</entry>
  <entry key="LiquidMetal.Cobalt.name">Molten Cobalt</entry>
  <entry key="LiquidMetal.Ardite.name">Molten Ardite</entry>
  <entry key="LiquidMetal.Bronze.name">Molten Bronze</entry>
  <entry key="LiquidMetal.AluBrass.name">Molten Aluminum Brass</entry>
  <entry key="LiquidMetal.Manyullyn.name">Molten Manyullyn</entry>
  <entry key="LiquidMetal.Alumite.name">Molten Alumite</entry>
  <entry key="LiquidMetal.Obsidian.name">Molten Obsidian</entry>
  <entry key="LiquidMetal.Steel.name">Molten Steel</entry>
  <entry key="LiquidMetal.Glass.name">Molten Glass</entry>
  <entry key="LiquidMetal.Stone.name">Seared Stone</entry>
  <entry key="LiquidMetal.Villager.name">Liquified Emerald</entry>
  <entry key="LiquidMetal.Cow.name">Blood</entry>
  
  <entry key="item.food.apple.diamond.name">Jeweled Apple</entry>
  <entry key="item.tconstruct.strangefood.edibleslime.name">Gelatinous Slime</entry>
  <entry key="item.tconstruct.canister.empty.name">Empty Canister</entry>
  <entry key="item.tconstruct.canister.miniheart.red.name">Miniature Red Heart</entry>
  <entry key="item.tconstruct.canister.heart.name">Heart Canister</entry>
  <entry key="item.tconstruct.glove.name">Dirtmover Gloves</entry>
  
  <entry key="SearedBlock.Table.name">Casting Table</entry>
  <entry key="SearedBlock.Faucet.name">Seared Faucet</entry>
  <entry key="SearedBlock.Basin.name">Casting Basin</entry>
  
  <entry key="entity.TConstruct.EdibleSlime.name">Blue Slime</entry>
  <entry key="entity.TConstruct.KingSlime.name">King Slime</entry>
  <entry key="entity.TConstruct.MiniGardy.name">Gardeslime</entry> 
  
  <entry key="key.tarmor">Armor Gui</entry>
  
  <entry key="death.one.smeltery">%1$s transformed into Soylent Green</entry>
  <entry key="death.two.smeltery">%1$s has fused with the Smeltery</entry>
  <entry key="death.three.smeltery">%1$s will be a stepping stone for our revolution!</entry>
  <entry key="death.four.smeltery">%1$s thought swimming in hot liquids was a good idea</entry>
  
  <entry key="death.attack.Landmine">%1$s watched their legs get blown off</entry>
  <entry key="death.fell.assist.Landmine">%1$s was doomed to fall by Landmine</entry>
  <entry key="death.attack.LandmineFireworkExplode">%1$s took a ride on a firework</entry>
  
  <entry key="parttype.Wood">Wooden</entry>
  <entry key="parttype.Stone">Stone</entry>
  <entry key="parttype.Iron">Iron</entry>
  <entry key="parttype.Flint">Flint</entry>
  <entry key="parttype.Cactus">Cactus</entry>
  <entry key="parttype.Bone">Bone</entry>
  <entry key="parttype.Obsidian">Obsidian</entry>
  <entry key="parttype.Slime">Slime</entry>
  <entry key="parttype.Paper">Paper</entry>
  <entry key="parttype.Cobalt">Cobalt</entry>
  <entry key="parttype.Ardite">Ardite</entry>
  <entry key="parttype.Manyullyn">Manyullyn</entry>
  <entry key="parttype.Copper">Copper</entry>
  <entry key="parttype.Bronze">Bronze</entry>
  <entry key="parttype.Alumite">Alumite</entry>
  <entry key="parttype.Steel">Steel</entry>
  <entry key="parttype.BlueSlime">Slime</entry>
  
</properties>